<hudson _class='hudson.model.Hudson'><assignedLabel></assignedLabel><mode>NORMAL</mode><nodeDescription>the master Jenkins node</nodeDescription><nodeName></nodeName><numExecutors>0</numExecutors><job _class='hudson.model.FreeStyleProject'><name>Archive</name><url>https://ci.inria.fr/inirobot/job/Archive/</url><color>blue</color></job><job _class='org.jenkinsci.plugins.workflow.job.WorkflowJob'><name>Aseba</name><url>https://ci.inria.fr/inirobot/job/Aseba/</url><color>blue</color></job><job _class='hudson.matrix.MatrixProject'><name>build-osx</name><url>https://ci.inria.fr/inirobot/job/build-osx/</url><color>disabled</color></job><job _class='hudson.matrix.MatrixProject'><name>build-windows</name><url>https://ci.inria.fr/inirobot/job/build-windows/</url><color>disabled</color></job><job _class='org.jenkinsci.plugins.workflow.job.WorkflowJob'><name>Dashel-pollsocketstream</name><url>https://ci.inria.fr/inirobot/job/Dashel-pollsocketstream/</url><color>blue</color></job><job _class='jenkins.branch.OrganizationFolder'><name>davidjsherman</name><url>https://ci.inria.fr/inirobot/job/davidjsherman/</url></job><job _class='org.jenkinsci.plugins.workflow.job.WorkflowJob'><name>DJS-pr17-merge</name><url>https://ci.inria.fr/inirobot/job/DJS-pr17-merge/</url><color>blue</color></job><job _class='org.jenkinsci.plugins.workflow.job.WorkflowJob'><name>DJS-pr17-playground</name><url>https://ci.inria.fr/inirobot/job/DJS-pr17-playground/</url><color>blue</color></job><job _class='org.jenkinsci.plugins.workflow.job.WorkflowJob'><name>Enki-old-api</name><url>https://ci.inria.fr/inirobot/job/Enki-old-api/</url><color>blue</color></job><job _class='org.jenkinsci.plugins.workflow.job.WorkflowJob'><name>Titwin-picking-squashed</name><url>https://ci.inria.fr/inirobot/job/Titwin-picking-squashed/</url><color>blue</color></job><job _class='org.jenkinsci.plugins.workflow.job.WorkflowJob'><name>Upstream-master</name><url>https://ci.inria.fr/inirobot/job/Upstream-master/</url><color>red</color></job><job _class='org.jenkinsci.plugins.workflow.job.WorkflowJob'><name>Zeroconf-current</name><url>https://ci.inria.fr/inirobot/job/Zeroconf-current/</url><color>blue</color></job><overallLoad></overallLoad><primaryView _class='hudson.model.AllView'><name>Tous</name><url>https://ci.inria.fr/inirobot/</url></primaryView><quietingDown>false</quietingDown><slaveAgentPort>24612</slaveAgentPort><unlabeledLoad _class='jenkins.model.UnlabeledLoadStatistics'></unlabeledLoad><useCrumbs>false</useCrumbs><useSecurity>true</useSecurity><view _class='hudson.model.AllView'><name>Tous</name><url>https://ci.inria.fr/inirobot/</url></view></hudson>